README.md
setup.cfg
setup.py
sfcommonutils/__init__.py
sfcommonutils/configutil.py
sfcommonutils/secretutil.py
sfcommonutils.egg-info/PKG-INFO
sfcommonutils.egg-info/SOURCES.txt
sfcommonutils.egg-info/dependency_links.txt
sfcommonutils.egg-info/requires.txt
sfcommonutils.egg-info/top_level.txt